ExperimentManager/__init__.py
ExperimentManager/experiment.py
ExperimentManager/global_manager.py
ExperimentManager/gpu_setup.py
ExperimentManager/metrics.py
ExperimentManager/run.py
ExperimentManager/saving.py
ExperimentManager/setup.py
ExperimentManager/signature.py
ExperimentManager/stdout_capturing.py
ExperimentManager/tb_utils.py
ExperimentManager/timer.py
ExperimentManager/utils.py
ExperimentManager/demo/__init__.py
ExperimentManager/demo/main.py
ExperimentManager-0.0.5.3.dist-info/LICENSE
ExperimentManager-0.0.5.3.dist-info/METADATA
ExperimentManager-0.0.5.3.dist-info/WHEEL
ExperimentManager-0.0.5.3.dist-info/top_level.txt
ExperimentManager-0.0.5.3.dist-info/RECORD
