Metadata-Version: 2.1
Name: ExperimentManager
Version: 0.0.5.3
Summary: A thoughtless and all-round experiment manager for Python
Home-page: https://github.com/victorruelle/ExperimentManager
Author: Victor Ruelle
Author-email: ruelle.victor@gmail.com
License: MIT
Platform: UNKNOWN
Requires-Dist: tensorflow
Requires-Dist: keras
Requires-Dist: superjson
Requires-Dist: wrapt
Requires-Dist: matplotlib
Requires-Dist: numpy
Requires-Dist: pydot
Requires-Dist: graphviz
